rtl/uart_rx.v
`timescale 1ns/1ps

module uart_rx # (
    parameter clk_freq = 50000000,
    parameter baud_rate = 9600,
    parameter oversample = 16,     // Matching your Day 2 oversample parameter
    parameter PARITY_TYPE = 0      // 0 for Even Parity, 1 for Odd Parity
)(
    input wire clk,
    input wire reset,
    input wire rx,
    input wire s_tick,             // 16x oversampling clock tick from baud_gen
    output reg rx_done,
    output reg parity_error,
    output reg [7:0] rx_data       // 8-bit output data payload
);

    // FSM State Encodings (3-bit matching your FSM tracking)
    localparam [2:0] IDLE   = 3'b000,
                     START  = 3'b001,
                     DATA   = 3'b010,
                     PARITY = 3'b011,
                     STOP   = 3'b100;

    // Internal Registers (Matching your structural style)
    reg [2:0] current_state, next_state;
    reg [3:0] s_count;         // Counts 16 slices per serial bit (0 to 15)
    reg [2:0] bit_index;       // Tracks 8 data payload bits (0 to 7)
    reg [7:0] data_buffer;     // Shift register for deserializing incoming data
    reg       parity_bit;      // Captures the parity bit directly from the rx wire

    // Reduction XOR logic matching your transmitter's parity system
    wire calc_parity;
    assign calc_parity = (PARITY_TYPE == 0) ? ^data_buffer : ~(^data_buffer);

    //-------------------------------------------------------------------------
    // 1. Sequential Logic Block (State & Counter Updates)
    //-------------------------------------------------------------------------
    always @(posedge clk or posedge reset) begin
        if (reset) begin
            current_state <= IDLE;
            s_count       <= 4'd0;
            bit_index     <= 3'd0;
            data_buffer   <= 8'd0;
            parity_bit    <= 1'b0;
        end else begin
            current_state <= next_state;
            
            case (current_state)
                IDLE: begin
                    s_count   <= 4'd0;
                    bit_index <= 3'd0;
                end
                
                START: begin
                    if (s_tick) begin
                        if (s_count == 4'd7) begin
                            s_count   <= 4'd0; // Reset slice counter for Data phase
                            bit_index <= 3'd0; // Reset index pointer
                        end else begin
                            s_count   <= s_count + 1'b1;
                        end
                    end
                end
                
                DATA: begin
                    if (s_tick) begin
                        if (s_count == 4'd15) begin
                            s_count     <= 4'd0;
                            data_buffer <= {rx, data_buffer[7:1]}; // Deserializing LSB-first
                            if (bit_index == 3'd7)
                                bit_index <= 3'd0;
                            else
                                bit_index <= bit_index + 1'b1;
                        end else begin
                            s_count <= s_count + 1'b1;
                        end
                    end
                end

                PARITY: begin
                    if (s_tick) begin
                        if (s_count == 4'd15) begin
                            s_count    <= 4'd0;
                            parity_bit <= rx; // Latch the parity bit value from line
                        end else begin
                            s_count <= s_count + 1'b1;
                        end
                    end
                end

                STOP: begin
                    if (s_tick) begin
                        if (s_count == 4'd15) begin
                            s_count <= 4'd0;
                        end else begin
                            s_count <= s_count + 1'b1;
                        end
                    end
                end
            endcase
        end
    end

    //-------------------------------------------------------------------------
    // 2. Combinational Next-State Logic Block
    //-------------------------------------------------------------------------
    always @(*) begin
        next_state = current_state;
        
        case (current_state)
            IDLE: begin
                if (~rx) // Low start bit edge detected
                    next_state = START;
            end
            
            START: begin
                if (s_tick && (s_count == 4'd7))
                    next_state = DATA;
            end
            
            DATA: begin
                if (s_tick && (s_count == 4'd15) && (bit_index == 3'd7))
                    next_state = PARITY;
            end
            
            PARITY: begin
                if (s_tick && (s_count == 4'd15))
                    next_state = STOP;
            end
            
            STOP: begin
                if (s_tick && (s_count == 4'd15))
                    next_state = IDLE;
            end
            
            default: next_state = IDLE;
        endcase
    end

    //-------------------------------------------------------------------------
    // 3. Registered Look-Ahead Output Logic
    //-------------------------------------------------------------------------
    always @(posedge clk or posedge reset) begin
        if (reset) begin
            rx_done      <= 1'b0;
            rx_data      <= 8'd0;
            parity_error <= 1'b0;
        end else begin
            // Pulse rx_done only on the final step exiting the STOP state
            if ((current_state == STOP) && s_tick && (s_count == 4'd15)) begin
                rx_done      <= 1'b1;
                rx_data      <= data_buffer;
                parity_error <= (parity_bit != calc_parity); // Flag if mismatch occurs
            end else begin
                rx_done <= 1'b0; // Auto-clear to maintain single clock cycle pulse
            end
        end
    end

endmodule

rtl/uart_tx.v
module uart_tx(
    input  wire       clk,
    input  wire        rst,
    input  wire        baud_tick,
    input  wire        tx_start,
    input  wire [7:0]  data_in,
    output reg         tx_out,
    output reg         tx_busy
);

    localparam IDLE   = 3'd0;
    localparam START  = 3'd1;
    localparam DATA   = 3'd2;
    localparam PARITY = 3'd3;
    localparam STOP   = 3'd4;

    reg [2:0] state, next_state;
    reg [7:0] shift_reg;
    reg [2:0] bit_cnt;
    reg       parity_bit;

    always @(posedge clk or posedge rst) begin
        if (rst)
            state <= IDLE;
        else
            state <= next_state;
    end

    always @(*) begin
        next_state = state;
        case (state)
            IDLE:    if (tx_start) next_state = START;
            START:   if (baud_tick) next_state = DATA;
            DATA:    if (baud_tick && bit_cnt == 3'd7) next_state = PARITY;
            PARITY:  if (baud_tick) next_state = STOP;
            STOP:    if (baud_tick) next_state = IDLE;
        endcase
    end

    always @(posedge clk or posedge rst) begin
        if (rst) begin
            tx_out     <= 1'b1;
            tx_busy    <= 1'b0;
            shift_reg  <= 8'd0;
            bit_cnt    <= 3'd0;
            parity_bit <= 1'b0;
        end else begin
            case (state)
                IDLE: begin
                    tx_out <= 1'b1;
                    if (tx_start) begin
                        shift_reg  <= data_in;
                        parity_bit <= ^data_in;
                        tx_busy    <= 1'b1;
                        bit_cnt    <= 3'd0;
                    end else begin
                        tx_busy <= 1'b0;
                    end
                end

                START: begin
                    tx_out <= 1'b0;
                end

                DATA: begin
                    tx_out <= shift_reg[0];
                    if (baud_tick) begin
                        shift_reg <= shift_reg >> 1;
                        bit_cnt   <= bit_cnt + 1'b1;
                    end
                end

                PARITY: begin
                    tx_out <= parity_bit;
                end

                STOP: begin
                    tx_out <= 1'b1;
                    if (baud_tick)
                        tx_busy <= 1'b0;
                end
            endcase
        end
    end

endmodule

rtl/baud_gen.v
module baud_gen # (
    //hash#(parameter list) is used to write reusable hardware code
    parameter clk_freq = 50000000,
    parameter baud_rate = 9600,
    parameter oversample = 1 // pass 16 for Rx
)(
    input clk,
    input reset,
    output baud_tick
);
//logic
localparam divisor = clk_freq/(baud_rate * oversample); //5208
reg[12:0] counter;

//always block
always @ (posedge clk or posedge reset) begin
    if(reset) begin
        counter <= 13'd0;
    end else begin
        if(counter == (divisor -1)) begin 
            counter <= 13'd0; // baud_tick
        end else begin 
            counter <= counter + 1'b1;
        end
    end
end
 
assign baud_tick = (counter == (divisor -1))? 1'b1 : 1'b0;
endmodule

rtl/uart_top.v
`timescale 1ns/1ps

module uart_top # (
    parameter clk_freq = 50000000,
    parameter baud_rate = 9600,
    parameter PARITY_TYPE = 0       // 0 for Even Parity, 1 for Odd Parity
)(
    input wire       clk,
    input wire       reset,         // Top-level board reset pin
    
    // Transmitter Interface Ports
    input wire       tx_start,
    input wire [7:0] tx_data,
    output wire      tx_serial,     // Physical outbound loop monitor pin
    output wire      tx_done,       // Connects to tx_busy status inversion
    
    // Receiver Interface Ports
    output wire      rx_done,
    output wire      parity_error,
    output wire [7:0] rx_data       
);

    // Internal Wire Routing Matrices
    wire s_tick;                    // Master 16x oversampling clock tick
    wire loopback_wire;             // Internal connection from tx output to rx input
    wire tx_busy_status;            // Captures your transmitter's busy signal

    //-------------------------------------------------------------------------
    // 1. Instantiation: The Master Timing Engine (16x Oversampling Mode)
    //-------------------------------------------------------------------------
    baud_gen #(
        .clk_freq(clk_freq),
        .baud_rate(baud_rate),
        .oversample(16)             
    ) master_baud_engine (
        .clk(clk),
        .reset(reset),
        .baud_tick(s_tick)          
    );

    //-------------------------------------------------------------------------
    // 2. Hardware Tick Divider: Creating the 1x Tx Pulse from the 16x Rx Pulse
    //-------------------------------------------------------------------------
    reg [3:0] tx_tick_counter;      
    reg       tx_tick;              

    always @(posedge clk or posedge reset) begin
        if (reset) begin
            tx_tick_counter <= 4'd0;
            tx_tick         <= 1'b0;
        end else begin
            tx_tick <= 1'b0;        
            if (s_tick) begin
                if (tx_tick_counter == 4'd15) begin
                    tx_tick_counter <= 4'd0;
                    tx_tick         <= 1'b1; 
                end else begin
                    tx_tick_counter <= tx_tick_counter + 1'b1;
                end
            end
        end
    end

    //-------------------------------------------------------------------------
    // 3. Instantiation: The Transmitter Module (Mapped to your exact port list)
    //-------------------------------------------------------------------------
    uart_tx transmitter_core (
        .clk(clk),
        .rst(reset),                 // Maps your 'rst' input to top-level reset
        .baud_tick(tx_tick),
        .tx_start(tx_start),
        .data_in(tx_data),           // Maps your 'data_in' input to top tx_data bus
        .tx_out(loopback_wire),      // Maps your 'tx_out' line to loopback trace
        .tx_busy(tx_busy_status)     // Capture the busy status wire
    );

    // Map external pins to match your testbench environment expectations
    assign tx_serial = loopback_wire;
    assign tx_done   = ~tx_busy_status; // Done when not busy

    //-------------------------------------------------------------------------
    // 4. Instantiation: The Receiver Module
    //-------------------------------------------------------------------------
    uart_rx #(
        .clk_freq(clk_freq),
        .baud_rate(baud_rate),
        .oversample(16),
        .PARITY_TYPE(PARITY_TYPE)
    ) receiver_core (
        .clk(clk),
        .reset(reset),
        .rx(loopback_wire),         // Listens directly to your tx_out trace!
        .s_tick(s_tick),            
        .rx_done(rx_done),
        .parity_error(parity_error),
        .rx_data(rx_data)
    );

endmodule

tb/uart_top_tb.v
`timescale 1ns/1ps

module uart_top_tb;

    // 1. Testbench Signals
    reg        tb_clk;
    reg        tb_reset;
    reg        tb_tx_start;
    reg  [7:0] tb_tx_data;
    wire       tb_tx_serial;
    wire       tb_tx_done;
    wire       tb_rx_done;
    wire       tb_parity_error;
    wire [7:0] tb_rx_data;

    // 2. Instantiate the Complete Loopback System Module
    uart_top #(
        .clk_freq(1000000),    // 1 MHz simulation clock
        .baud_rate(9600),      // 9600 Baud
        .PARITY_TYPE(0)        // Even Parity Mode
    ) uut_top (
        .clk(tb_clk),
        .reset(tb_reset),
        .tx_start(tb_tx_start),
        .tx_data(tb_tx_data),
        .tx_serial(tb_tx_serial),
        .tx_done(tb_tx_done),
        .rx_done(tb_rx_done),
        .parity_error(tb_parity_error),
        .rx_data(tb_rx_data)
    );

    // 3. Generate 1 MHz Master System Clock (1000ns period)
    always begin
        #500 tb_clk = ~tb_clk;
    end

    // 4. Test Execution Timeline
    initial begin
        $dumpfile("top_waveform.vcd");
        $dumpvars(0, uart_top_tb);
        
        // Initial State
        tb_clk      = 0;
        tb_reset    = 1;
        tb_tx_start = 0;
        tb_tx_data  = 8'd0;
        #2000;
        
        // Release Reset
        tb_reset = 0;
        #5000;
        
        // --- TEST CASE 1: Send your target 10101010 pattern through the loop ---
        $display("[SYSTEM TEST] Loading 0xAA (8'b10101010) into Transmitter...");
        tb_tx_data  = 8'hAA;
        tb_tx_start = 1;        // Press the transmit button
        #1000;                  // Hold for 1 clock cycle pulse
        tb_tx_start = 0;        // Release button
        
        // Wait for the loopback to complete processing
        // 11 bits total (1 start + 8 data + 1 parity + 1 stop) at 9600 baud takes ~1.15ms
        @(posedge tb_rx_done);  // Pause execution until the receiver finishes parsing
        #10000;                 // Hold view window
        
        $display("[SYSTEM TEST] Success! Received Parallel Byte: 0x%h", tb_rx_data);
        $display("[SYSTEM TEST] Parity Error Status: %b", tb_parity_error);
        
        #50000;
        $display("[SIM COMPLETE] Top Level Loopback Verified.");
        $finish;
    end

endmodule

sim/top_waveform.vcd
$date
	Wed Jun 24 14:02:43 2026
$end
$version
	Icarus Verilog
$end
$timescale
	1ps
$end
$scope module uart_top_tb $end
$var wire 1 ! tb_tx_serial $end
$var wire 1 " tb_tx_done $end
$var wire 1 # tb_rx_done $end
$var wire 8 $ tb_rx_data [7:0] $end
$var wire 1 % tb_parity_error $end
$var reg 1 & tb_clk $end
$var reg 1 ' tb_reset $end
$var reg 8 ( tb_tx_data [7:0] $end
$var reg 1 ) tb_tx_start $end
$scope module uut_top $end
$var wire 1 & clk $end
$var wire 1 ' reset $end
$var wire 8 * tx_data [7:0] $end
$var wire 1 " tx_done $end
$var wire 1 ! tx_serial $end
$var wire 1 ) tx_start $end
$var wire 1 + tx_busy_status $end
$var wire 1 , s_tick $end
$var wire 1 # rx_done $end
$var wire 8 - rx_data [7:0] $end
$var wire 1 % parity_error $end
$var wire 1 . loopback_wire $end
$var parameter 32 / PARITY_TYPE $end
$var parameter 32 0 baud_rate $end
$var parameter 32 1 clk_freq $end
$var reg 1 2 tx_tick $end
$var reg 4 3 tx_tick_counter [3:0] $end
$scope module master_baud_engine $end
$var wire 1 & clk $end
$var wire 1 ' reset $end
$var wire 1 , baud_tick $end
$var parameter 32 4 baud_rate $end
$var parameter 32 5 clk_freq $end
$var parameter 64 6 divisor $end
$var parameter 32 7 oversample $end
$var reg 13 8 counter [12:0] $end
$upscope $end
$scope module receiver_core $end
$var wire 1 & clk $end
$var wire 1 ' reset $end
$var wire 1 , s_tick $end
$var wire 1 . rx $end
$var wire 1 9 calc_parity $end
$var parameter 3 : DATA $end
$var parameter 3 ; IDLE $end
$var parameter 3 < PARITY $end
$var parameter 32 = PARITY_TYPE $end
$var parameter 3 > START $end
$var parameter 3 ? STOP $end
$var parameter 32 @ baud_rate $end
$var parameter 32 A clk_freq $end
$var parameter 32 B oversample $end
$var reg 3 C bit_index [2:0] $end
$var reg 3 D current_state [2:0] $end
$var reg 8 E data_buffer [7:0] $end
$var reg 3 F next_state [2:0] $end
$var reg 1 G parity_bit $end
$var reg 1 % parity_error $end
$var reg 8 H rx_data [7:0] $end
$var reg 1 # rx_done $end
$var reg 4 I s_count [3:0] $end
$upscope $end
$scope module transmitter_core $end
$var wire 1 2 baud_tick $end
$var wire 1 & clk $end
$var wire 8 J data_in [7:0] $end
$var wire 1 ' rst $end
$var wire 1 ) tx_start $end
$var parameter 3 K DATA $end
$var parameter 3 L IDLE $end
$var parameter 3 M PARITY $end
$var parameter 3 N START $end
$var parameter 3 O STOP $end
$var reg 3 P bit_cnt [2:0] $end
$var reg 3 Q next_state [2:0] $end
$var reg 1 R parity_bit $end
$var reg 8 S shift_reg [7:0] $end
$var reg 3 T state [2:0] $end
$var reg 1 + tx_busy $end
$var reg 1 . tx_out $end
$upscope $end
$upscope $end
$upscope $end
$enddefinitions $end
$comment Show the parameter values. $end
$dumpall
b100 O
b1 N
b11 M
b0 L
b10 K
b10000 B
b11110100001001000000 A
b10010110000000 @
b100 ?
b1 >
b0 =
b11 <
b0 ;
b10 :
b10000 7
b110 6
b11110100001001000000 5
b10010110000000 4
b11110100001001000000 1
b10010110000000 0
b0 /
$end
#0
$dumpvars
b0 T
b0 S
0R
b0 Q
b0 P
b0 J
b0 I
b0 H
0G
b0 F
b0 E
b0 D
b0 C
09
b0 8
b0 3
02
1.
b0 -
0,
0+
b0 *
0)
b0 (
1'
0&
0%
b0 $
0#
1"
1!
$end
#500000
1&
#1000000
0&
#1500000
1&
#2000000
0&
0'
#2500000
b1 8
1&
#3000000
0&
#3500000
b10 8
1&
#4000000
0&
#4500000
b11 8
1&
#5000000
0&
#5500000
b100 8
1&
#6000000
0&
#6500000
1,
b101 8
1&
#7000000
b1 Q
0&
1)
b10101010 (
b10101010 *
b10101010 J
#7500000
0,
0"
b0 8
b1 T
1+
b10101010 S
b1 3
1&
#8000000
0&
0)
#8500000
b1 F
0!
0.
b1 8
1&
#9000000
0&
#9500000
b10 8
b1 D
1&
#10000000
0&
#10500000
b11 8
1&
#11000000
0&
#11500000
b100 8
1&
#12000000
0&
#12500000
1,
b101 8
1&
#13000000
0&
#13500000
0,
b0 8
b1 I
b10 3
1&
#14000000
0&
#14500000
b1 8
1&
#15000000
0&
#15500000
b10 8
1&
#16000000
0&
#16500000
b11 8
1&
#17000000
0&
#17500000
b100 8
1&
#18000000
0&
#18500000
1,
b101 8
1&
#19000000
0&
#19500000
0,
b0 8
b10 I
b11 3
1&
#20000000
0&
#20500000
b1 8
1&
#21000000
0&
#21500000
b10 8
1&
#22000000
0&
#22500000
b11 8
1&
#23000000
0&
#23500000
b100 8
1&
#24000000
0&
#24500000
1,
b101 8
1&
#25000000
0&
#25500000
0,
b0 8
b11 I
b100 3
1&
#26000000
0&
#26500000
b1 8
1&
#27000000
0&
#27500000
b10 8
1&
#28000000
0&
#28500000
b11 8
1&
#29000000
0&
#29500000
b100 8
1&
#30000000
0&
#30500000
1,
b101 8
1&
#31000000
0&
#31500000
0,
b0 8
b100 I
b101 3
1&
#32000000
0&
#32500000
b1 8
1&
#33000000
0&
#33500000
b10 8
1&
#34000000
0&
#34500000
b11 8
1&
#35000000
0&
#35500000
b100 8
1&
#36000000
0&
#36500000
1,
b101 8
1&
#37000000
0&
#37500000
0,
b0 8
b101 I
b110 3
1&
#38000000
0&
#38500000
b1 8
1&
#39000000
0&
#39500000
b10 8
1&
#40000000
0&
#40500000
b11 8
1&
#41000000
0&
#41500000
b100 8
1&
#42000000
0&
#42500000
1,
b101 8
1&
#43000000
0&
#43500000
0,
b0 8
b110 I
b111 3
1&
#44000000
0&
#44500000
b1 8
1&
#45000000
0&
#45500000
b10 8
1&
#46000000
0&
#46500000
b11 8
1&
#47000000
0&
#47500000
b100 8
1&
#48000000
0&
#48500000
1,
b101 8
1&
#49000000
0&
#49500000
0,
b1 F
b0 8
b111 I
b1000 3
1&
#50000000
0&
#50500000
b1 8
1&
#51000000
0&
#51500000
b10 8
1&
#52000000
0&
#52500000
b11 8
1&
#53000000
0&
#53500000
b100 8
1&
#54000000
0&
#54500000
b10 F
1,
b101 8
1&
#55000000
0&
#55500000
0,
b0 8
b0 I
b10 D
b1001 3
1&
#56000000
0&
#56500000
b1 8
1&
#57000000
0&
#57500000
b10 8
1&
#58000000
0&
#58500000
b11 8
1&
#59000000
0&
#59500000
b100 8
1&
#60000000
0&
#60500000
1,
b101 8
1&
#61000000
0&
#61500000
0,
b0 8
b1 I
b1010 3
1&
#62000000
0&
#62500000
b1 8
1&
#63000000
0&
#63500000
b10 8
1&
#64000000
0&
#64500000
b11 8
1&
#65000000
0&
#65500000
b100 8
1&
#66000000
0&
#66500000
1,
b101 8
1&
#67000000
0&
#67500000
0,
b0 8
b10 I
b1011 3
1&
#68000000
0&
#68500000
b1 8
1&
#69000000
0&
#69500000
b10 8
1&
#70000000
0&
#70500000
b11 8
1&
#71000000
0&
#71500000
b100 8
1&
#72000000
0&
#72500000
1,
b101 8
1&
#73000000
0&
#73500000
0,
b0 8
b11 I
b1100 3
1&
#74000000
0&
#74500000
b1 8
1&
#75000000
0&
#75500000
b10 8
1&
#76000000
0&
#76500000
b11 8
1&
#77000000
0&
#77500000
b100 8
1&
#78000000
0&
#78500000
1,
b101 8
1&
#79000000
0&
#79500000
0,
b0 8
b100 I
b1101 3
1&
#80000000
0&
#80500000
b1 8
1&
#81000000
0&
#81500000
b10 8
1&
#82000000
0&
#82500000
b11 8
1&
#83000000
0&
#83500000
b100 8
1&
#84000000
0&
#84500000
1,
b101 8
1&
#85000000
0&
#85500000
0,
b0 8
b101 I
b1110 3
1&
#86000000
0&
#86500000
b1 8
1&
#87000000
0&
#87500000
b10 8
1&
#88000000
0&
#88500000
b11 8
1&
#89000000
0&
#89500000
b100 8
1&
#90000000
0&
#90500000
1,
b101 8
1&
#91000000
0&
#91500000
0,
b0 8
b110 I
b1111 3
1&
#92000000
0&
#92500000
b1 8
1&
#93000000
0&
#93500000
b10 8
1&
#94000000
0&
#94500000
b11 8
1&
#95000000
0&
#95500000
b100 8
1&
#96000000
0&
#96500000
1,
b101 8
1&
#97000000
0&
#97500000
0,
b10 Q
b0 8
b111 I
12
b0 3
1&
#98000000
0&
#98500000
02
b10 T
b1 8
1&
#99000000
0&
#99500000
b10 8
1&
#100000000
0&
#100500000
b11 8
1&
#101000000
0&
#101500000
b100 8
1&
#102000000
0&
#102500000
1,
b101 8
1&
#103000000
0&
#103500000
0,
b0 8
b1000 I
b1 3
1&
#104000000
0&
#104500000
b1 8
1&
#105000000
0&
#105500000
b10 8
1&
#106000000
0&
#106500000
b11 8
1&
#107000000
0&
#107500000
b100 8
1&
#108000000
0&
#108500000
1,
b101 8
1&
#109000000
0&
#109500000
0,
b0 8
b1001 I
b10 3
1&
#110000000
0&
#110500000
b1 8
1&
#111000000
0&
#111500000
b10 8
1&
#112000000
0&
#112500000
b11 8
1&
#113000000
0&
#113500000
b100 8
1&
#114000000
0&
#114500000
1,
b101 8
1&
#115000000
0&
#115500000
0,
b0 8
b1010 I
b11 3
1&
#116000000
0&
#116500000
b1 8
1&
#117000000
0&
#117500000
b10 8
1&
#118000000
0&
#118500000
b11 8
1&
#119000000
0&
#119500000
b100 8
1&
#120000000
0&
#120500000
1,
b101 8
1&
#121000000
0&
#121500000
0,
b0 8
b1011 I
b100 3
1&
#122000000
0&
#122500000
b1 8
1&
#123000000
0&
#123500000
b10 8
1&
#124000000
0&
#124500000
b11 8
1&
#125000000
0&
#125500000
b100 8
1&
#126000000
0&
#126500000
1,
b101 8
1&
#127000000
0&
#127500000
0,
b0 8
b1100 I
b101 3
1&
#128000000
0&
#128500000
b1 8
1&
#129000000
0&
#129500000
b10 8
1&
#130000000
0&
#130500000
b11 8
1&
#131000000
0&
#131500000
b100 8
1&
#132000000
0&
#132500000
1,
b101 8
1&
#133000000
0&
#133500000
0,
b0 8
b1101 I
b110 3
1&
#134000000
0&
#134500000
b1 8
1&
#135000000
0&
#135500000
b10 8
1&
#136000000
0&
#136500000
b11 8
1&
#137000000
0&
#137500000
b100 8
1&
#138000000
0&
#138500000
1,
b101 8
1&
#139000000
0&
#139500000
0,
b0 8
b1110 I
b111 3
1&
#140000000
0&
#140500000
b1 8
1&
#141000000
0&
#141500000
b10 8
1&
#142000000
0&
#142500000
b11 8
1&
#143000000
0&
#143500000
b100 8
1&
#144000000
0&
#144500000
1,
b101 8
1&
#145000000
0&
#145500000
0,
b0 8
b1111 I
b1000 3
1&
#146000000
0&
#146500000
b1 8
1&
#147000000
0&
#147500000
b10 8
1&
#148000000
0&
#148500000
b11 8
1&
#149000000
0&
#149500000
b100 8
1&
#150000000
0&
#150500000
1,
b101 8
1&
#151000000
0&
#151500000
0,
b0 8
b1 C
b0 I
b1001 3
1&
#152000000
0&
#152500000
b1 8
1&
#153000000
0&
#153500000
b10 8
1&
#154000000
0&
#154500000
b11 8
1&
#155000000
0&
#155500000
b100 8
1&
#156000000
0&
#156500000
1,
b101 8
1&
#157000000
0&
#157500000
0,
b0 8
b1 I
b1010 3
1&
#158000000
0&
#158500000
b1 8
1&
#159000000
0&
#159500000
b10 8
1&
#160000000
0&
#160500000
b11 8
1&
#161000000
0&
#161500000
b100 8
1&
#162000000
0&
#162500000
1,
b101 8
1&
#163000000
0&
#163500000
0,
b0 8
b10 I
b1011 3
1&
#164000000
0&
#164500000
b1 8
1&
#165000000
0&
#165500000
b10 8
1&
#166000000
0&
#166500000
b11 8
1&
#167000000
0&
#167500000
b100 8
1&
#168000000
0&
#168500000
1,
b101 8
1&
#169000000
0&
#169500000
0,
b0 8
b11 I
b1100 3
1&
#170000000
0&
#170500000
b1 8
1&
#171000000
0&
#171500000
b10 8
1&
#172000000
0&
#172500000
b11 8
1&
#173000000
0&
#173500000
b100 8
1&
#174000000
0&
#174500000
1,
b101 8
1&
#175000000
0&
#175500000
0,
b0 8
b100 I
b1101 3
1&
#176000000
0&
#176500000
b1 8
1&
#177000000
0&
#177500000
b10 8
1&
#178000000
0&
#178500000
b11 8
1&
#179000000
0&
#179500000
b100 8
1&
#180000000
0&
#180500000
1,
b101 8
1&
#181000000
0&
#181500000
0,
b0 8
b101 I
b1110 3
1&
#182000000
0&
#182500000
b1 8
1&
#183000000
0&
#183500000
b10 8
1&
#184000000
0&
#184500000
b11 8
1&
#185000000
0&
#185500000
b100 8
1&
#186000000
0&
#186500000
1,
b101 8
1&
#187000000
0&
#187500000
0,
b0 8
b110 I
b1111 3
1&
#188000000
0&
#188500000
b1 8
1&
#189000000
0&
#189500000
b10 8
1&
#190000000
0&
#190500000
b11 8
1&
#191000000
0&
#191500000
b100 8
1&
#192000000
0&
#192500000
1,
b101 8
1&
#193000000
0&
#193500000
0,
b0 8
b111 I
12
b0 3
1&
#194000000
0&
#194500000
02
b1 P
b1010101 S
b1 8
1&
#195000000
0&
#195500000
b10 8
1!
1.
1&
#196000000
0&
#196500000
b11 8
1&
#197000000
0&
#197500000
b100 8
1&
#198000000
0&
#198500000
1,
b101 8
1&
#199000000
0&
#199500000
0,
b0 8
b1000 I
b1 3
1&
#200000000
0&
#200500000
b1 8
1&
#201000000
0&
#201500000
b10 8
1&
#202000000
0&
#202500000
b11 8
1&
#203000000
0&
#203500000
b100 8
1&
#204000000
0&
#204500000
1,
b101 8
1&
#205000000
0&
#205500000
0,
b0 8
b1001 I
b10 3
1&
#206000000
0&
#206500000
b1 8
1&
#207000000
0&
#207500000
b10 8
1&
#208000000
0&
#208500000
b11 8
1&
#209000000
0&
#209500000
b100 8
1&
#210000000
0&
#210500000
1,
b101 8
1&
#211000000
0&
#211500000
0,
b0 8
b1010 I
b11 3
1&
#212000000
0&
#212500000
b1 8
1&
#213000000
0&
#213500000
b10 8
1&
#214000000
0&
#214500000
b11 8
1&
#215000000
0&
#215500000
b100 8
1&
#216000000
0&
#216500000
1,
b101 8
1&
#217000000
0&
#217500000
0,
b0 8
b1011 I
b100 3
1&
#218000000
0&
#218500000
b1 8
1&
#219000000
0&
#219500000
b10 8
1&
#220000000
0&
#220500000
b11 8
1&
#221000000
0&
#221500000
b100 8
1&
#222000000
0&
#222500000
1,
b101 8
1&
#223000000
0&
#223500000
0,
b0 8
b1100 I
b101 3
1&
#224000000
0&
#224500000
b1 8
1&
#225000000
0&
#225500000
b10 8
1&
#226000000
0&
#226500000
b11 8
1&
#227000000
0&
#227500000
b100 8
1&
#228000000
0&
#228500000
1,
b101 8
1&
#229000000
0&
#229500000
0,
b0 8
b1101 I
b110 3
1&
#230000000
0&
#230500000
b1 8
1&
#231000000
0&
#231500000
b10 8
1&
#232000000
0&
#232500000
b11 8
1&
#233000000
0&
#233500000
b100 8
1&
#234000000
0&
#234500000
1,
b101 8
1&
#235000000
0&
#235500000
0,
b0 8
b1110 I
b111 3
1&
#236000000
0&
#236500000
b1 8
1&
#237000000
0&
#237500000
b10 8
1&
#238000000
0&
#238500000
b11 8
1&
#239000000
0&
#239500000
b100 8
1&
#240000000
0&
#240500000
1,
b101 8
1&
#241000000
0&
#241500000
0,
b0 8
b1111 I
b1000 3
1&
#242000000
0&
#242500000
b1 8
1&
#243000000
0&
#243500000
b10 8
1&
#244000000
0&
#244500000
b11 8
1&
#245000000
0&
#245500000
b100 8
1&
#246000000
0&
#246500000
1,
b101 8
1&
#247000000
0&
#247500000
0,
b0 8
b10 C
19
b10000000 E
b0 I
b1001 3
1&
#248000000
0&
#248500000
b1 8
1&
#249000000
0&
#249500000
b10 8
1&
#250000000
0&
#250500000
b11 8
1&
#251000000
0&
#251500000
b100 8
1&
#252000000
0&
#252500000
1,
b101 8
1&
#253000000
0&
#253500000
0,
b0 8
b1 I
b1010 3
1&
#254000000
0&
#254500000
b1 8
1&
#255000000
0&
#255500000
b10 8
1&
#256000000
0&
#256500000
b11 8
1&
#257000000
0&
#257500000
b100 8
1&
#258000000
0&
#258500000
1,
b101 8
1&
#259000000
0&
#259500000
0,
b0 8
b10 I
b1011 3
1&
#260000000
0&
#260500000
b1 8
1&
#261000000
0&
#261500000
b10 8
1&
#262000000
0&
#262500000
b11 8
1&
#263000000
0&
#263500000
b100 8
1&
#264000000
0&
#264500000
1,
b101 8
1&
#265000000
0&
#265500000
0,
b0 8
b11 I
b1100 3
1&
#266000000
0&
#266500000
b1 8
1&
#267000000
0&
#267500000
b10 8
1&
#268000000
0&
#268500000
b11 8
1&
#269000000
0&
#269500000
b100 8
1&
#270000000
0&
#270500000
1,
b101 8
1&
#271000000
0&
#271500000
0,
b0 8
b100 I
b1101 3
1&
#272000000
0&
#272500000
b1 8
1&
#273000000
0&
#273500000
b10 8
1&
#274000000
0&
#274500000
b11 8
1&
#275000000
0&
#275500000
b100 8
1&
#276000000
0&
#276500000
1,
b101 8
1&
#277000000
0&
#277500000
0,
b0 8
b101 I
b1110 3
1&
#278000000
0&
#278500000
b1 8
1&
#279000000
0&
#279500000
b10 8
1&
#280000000
0&
#280500000
b11 8
1&
#281000000
0&
#281500000
b100 8
1&
#282000000
0&
#282500000
1,
b101 8
1&
#283000000
0&
#283500000
0,
b0 8
b110 I
b1111 3
1&
#284000000
0&
#284500000
b1 8
1&
#285000000
0&
#285500000
b10 8
1&
#286000000
0&
#286500000
b11 8
1&
#287000000
0&
#287500000
b100 8
1&
#288000000
0&
#288500000
1,
b101 8
1&
#289000000
0&
#289500000
0,
b0 8
b111 I
12
b0 3
1&
#290000000
0&
#290500000
02
b10 P
b101010 S
b1 8
1&
#291000000
0&
#291500000
b10 8
0!
0.
1&
#292000000
0&
#292500000
b11 8
1&
#293000000
0&
#293500000
b100 8
1&
#294000000
0&
#294500000
1,
b101 8
1&
#295000000
0&
#295500000
0,
b0 8
b1000 I
b1 3
1&
#296000000
0&
#296500000
b1 8
1&
#297000000
0&
#297500000
b10 8
1&
#298000000
0&
#298500000
b11 8
1&
#299000000
0&
#299500000
b100 8
1&
#300000000
0&
#300500000
1,
b101 8
1&
#301000000
0&
#301500000
0,
b0 8
b1001 I
b10 3
1&
#302000000
0&
#302500000
b1 8
1&
#303000000
0&
#303500000
b10 8
1&
#304000000
0&
#304500000
b11 8
1&
#305000000
0&
#305500000
b100 8
1&
#306000000
0&
#306500000
1,
b101 8
1&
#307000000
0&
#307500000
0,
b0 8
b1010 I
b11 3
1&
#308000000
0&
#308500000
b1 8
1&
#309000000
0&
#309500000
b10 8
1&
#310000000
0&
#310500000
b11 8
1&
#311000000
0&
#311500000
b100 8
1&
#312000000
0&
#312500000
1,
b101 8
1&
#313000000
0&
#313500000
0,
b0 8
b1011 I
b100 3
1&
#314000000
0&
#314500000
b1 8
1&
#315000000
0&
