rtl/uart_rx.v
`timescale 1ns/1ps

module uart_rx # (
    parameter clk_freq = 50000000,
    parameter baud_rate = 9600,
    parameter oversample = 16,     // Matching your Day 2 oversample parameter
    parameter PARITY_TYPE = 0      // 0 for Even Parity, 1 for Odd Parity
)(
    input wire clk,
    input wire reset,
    input wire rx,
    input wire s_tick,             // 16x oversampling clock tick from baud_gen
    output reg rx_done,
    output reg parity_error,
    output reg [7:0] rx_data       // 8-bit output data payload
);

    // FSM State Encodings (3-bit matching your FSM tracking)
    localparam [2:0] IDLE   = 3'b000,
                     START  = 3'b001,
                     DATA   = 3'b010,
                     PARITY = 3'b011,
                     STOP   = 3'b100;

    // Internal Registers (Matching your structural style)
    reg [2:0] current_state, next_state;
    reg [3:0] s_count;         // Counts 16 slices per serial bit (0 to 15)
    reg [2:0] bit_index;       // Tracks 8 data payload bits (0 to 7)
    reg [7:0] data_buffer;     // Shift register for deserializing incoming data
    reg       parity_bit;      // Captures the parity bit directly from the rx wire

    // Reduction XOR logic matching your transmitter's parity system
    wire calc_parity;
    assign calc_parity = (PARITY_TYPE == 0) ? ^data_buffer : ~(^data_buffer);

    //-------------------------------------------------------------------------
    // 1. Sequential Logic Block (State & Counter Updates)
    //-------------------------------------------------------------------------
    always @(posedge clk or posedge reset) begin
        if (reset) begin
            current_state <= IDLE;
            s_count       <= 4'd0;
            bit_index     <= 3'd0;
            data_buffer   <= 8'd0;
            parity_bit    <= 1'b0;
        end else begin
            current_state <= next_state;
            
            case (current_state)
                IDLE: begin
                    s_count   <= 4'd0;
                    bit_index <= 3'd0;
                end
                
                START: begin
                    if (s_tick) begin
                        if (s_count == 4'd7) begin
                            s_count   <= 4'd0; // Reset slice counter for Data phase
                            bit_index <= 3'd0; // Reset index pointer
                        end else begin
                            s_count   <= s_count + 1'b1;
                        end
                    end
                end
                
                DATA: begin
                    if (s_tick) begin
                        if (s_count == 4'd15) begin
                            s_count     <= 4'd0;
                            data_buffer <= {rx, data_buffer[7:1]}; // Deserializing LSB-first
                            if (bit_index == 3'd7)
                                bit_index <= 3'd0;
                            else
                                bit_index <= bit_index + 1'b1;
                        end else begin
                            s_count <= s_count + 1'b1;
                        end
                    end
                end

                PARITY: begin
                    if (s_tick) begin
                        if (s_count == 4'd15) begin
                            s_count    <= 4'd0;
                            parity_bit <= rx; // Latch the parity bit value from line
                        end else begin
                            s_count <= s_count + 1'b1;
                        end
                    end
                end

                STOP: begin
                    if (s_tick) begin
                        if (s_count == 4'd15) begin
                            s_count <= 4'd0;
                        end else begin
                            s_count <= s_count + 1'b1;
                        end
                    end
                end
            endcase
        end
    end

    //-------------------------------------------------------------------------
    // 2. Combinational Next-State Logic Block
    //-------------------------------------------------------------------------
    always @(*) begin
        next_state = current_state;
        
        case (current_state)
            IDLE: begin
                if (~rx) // Low start bit edge detected
                    next_state = START;
            end
            
            START: begin
                if (s_tick && (s_count == 4'd7))
                    next_state = DATA;
            end
            
            DATA: begin
                if (s_tick && (s_count == 4'd15) && (bit_index == 3'd7))
                    next_state = PARITY;
            end
            
            PARITY: begin
                if (s_tick && (s_count == 4'd15))
                    next_state = STOP;
            end
            
            STOP: begin
                if (s_tick && (s_count == 4'd15))
                    next_state = IDLE;
            end
            
            default: next_state = IDLE;
        endcase
    end

    //-------------------------------------------------------------------------
    // 3. Registered Look-Ahead Output Logic
    //-------------------------------------------------------------------------
    always @(posedge clk or posedge reset) begin
        if (reset) begin
            rx_done      <= 1'b0;
            rx_data      <= 8'd0;
            parity_error <= 1'b0;
        end else begin
            // Pulse rx_done only on the final step exiting the STOP state
            if ((current_state == STOP) && s_tick && (s_count == 4'd15)) begin
                rx_done      <= 1'b1;
                rx_data      <= data_buffer;
                parity_error <= (parity_bit != calc_parity); // Flag if mismatch occurs
            end else begin
                rx_done <= 1'b0; // Auto-clear to maintain single clock cycle pulse
            end
        end
    end

endmodule

rtl/baud_gen.v
module baud_gen # (
    //hash#(parameter list) is used to write reusable hardware code
    parameter clk_freq = 50000000,
    parameter baud_rate = 9600,
    parameter oversample = 1 // pass 16 for Rx
)(
    input clk,
    input reset,
    output baud_tick
);
//logic
localparam divisor = clk_freq/(baud_rate * oversample); //5208
reg[12:0] counter;

//always block
always @ (posedge clk or posedge reset) begin
    if(reset) begin
        counter <= 13'd0;
    end else begin
        if(counter == (divisor -1)) begin 
            counter <= 13'd0; // baud_tick
        end else begin 
            counter <= counter + 1'b1;
        end
    end
end
 
assign baud_tick = (counter == (divisor -1))? 1'b1 : 1'b0;
endmodule

tb/uart_rx_tb.v
`timescale 1ns/1ps

module uart_rx_tb;

    // 1. Testbench Signals
    reg        tb_clk;
    reg        tb_reset;
    reg        tb_rx;
    wire       tb_s_tick;
    wire       tb_rx_done;
    wire       tb_parity_error;
    wire [7:0] tb_rx_data;

    // 2. Instantiate the Clock/Timing Engine (Configured for 16x Oversampling)
    baud_gen #(
        .clk_freq(1000000),    // 1 MHz fake clock to keep simulation tight
        .baud_rate(9600),      // 9600 Baud
        .oversample(16)        // 16x oversampling mode enabled for RX support
    ) uut_baud (
        .clk(tb_clk),
        .reset(tb_reset),
        .baud_tick(tb_s_tick)  // Feeds the 16x oversample ticks directly to the RX
    );

    // 3. Instantiate your Re-Engineered Receiver Module
    uart_rx #(
        .clk_freq(1000000),
        .baud_rate(9600),
        .oversample(16),
        .PARITY_TYPE(0)        // 0 for Even Parity (Matches our test vector calculation)
    ) uut_rx (
        .clk(tb_clk),
        .reset(tb_reset),
        .rx(tb_rx),
        .s_tick(tb_s_tick),
        .rx_done(tb_rx_done),
        .parity_error(tb_parity_error),
        .rx_data(tb_rx_data)
    );

    // 4. Generate the Master System Clock Heartbeat (1 MHz -> 1000ns Period)
    always begin
        #500 tb_clk = ~tb_clk; // Toggle every 500ns to yield a 1us clock period
    end

    // Standard local time representation for 1 Baud duration at 9600 Baud
    // 1 / 9600 seconds = ~104,166 nanoseconds
    localparam BAUD_PERIOD = 104166;

    // 5. Test Stimulus Task (Automates feeding a frame onto the serial wire)
    task send_uart_frame;
        input [7:0] test_byte;
        integer i;
        reg calc_even_parity;
        begin
            // Calculate Even Parity bit locally within the task loop
            calc_even_parity = ^test_byte; 
            
            $display("[TX SIM] Sending Byte: 0x%h (Binary: %b)", test_byte, test_byte);
            
            // A. Start Bit (Pull line LOW)
            tb_rx = 1'b0;
            #BAUD_PERIOD;
            
            // B. Data Bits (LSB-first sequence)
            for (i = 0; i < 8; i = i + 1) begin
                tb_rx = test_byte[i];
                #BAUD_PERIOD;
            end
            
            // C. Send Parity Bit
            tb_rx = calc_even_parity;
            #BAUD_PERIOD;
            
            // D. Stop Bit (Drive line back HIGH)
            tb_rx = 1'b1;
            #BAUD_PERIOD;
            
            $display("[TX SIM] Finished transmitting frame.");
        end
    endtask

    //  task to intentionally inject a corrupted parity bit frame
    task send_corrupted_frame;
        input [7:0] test_byte;
        integer i;
        begin
            $display("[TX SIM WARNING] Injecting Corrupted Frame with bad parity bit!");
            // Start Bit
            tb_rx = 1'b0; #BAUD_PERIOD;
            // Data Bits
            for (i = 0; i < 8; i = i + 1) begin
                tb_rx = test_byte[i]; #BAUD_PERIOD;
            end
            // Inject WRONG parity bit intentionally (Inverting correct even parity)
            tb_rx = ~(^test_byte); 
            #BAUD_PERIOD;
            // Stop Bit
            tb_rx = 1'b1; #BAUD_PERIOD;
        end
    endtask

    // 6. Chronological Test Stimulus Execution
    // 6. Chronological Test Stimulus Execution
    initial begin
        // Setup local waveform tracking dump files for GTKWave
        $dumpfile("waveform.vcd");
        $dumpvars(0, uart_rx_tb);
        
        // Initial conditions
        tb_clk   = 0;
        tb_reset = 1;
        tb_rx    = 1; // Line rests at logic HIGH
        #2000;
        
        // Release reset line
        tb_reset = 0;
        #5000;
        
        // --- TEST CASE 1: Target alternating pattern 8'b10101010 (8'hAA) ---
        // Expected behavior: rx_data outputs 8'hAA, rx_done pulses, parity_error stays 0
        send_uart_frame(8'hAA); 
        #50000; // Hold gap window between frames
        
        // --- TEST CASE 2: Send a corrupted data frame to verify parity error flags ---
        // Expected behavior: rx_done pulses, parity_error asserts HIGH to catch corruption
        send_corrupted_frame(8'hAA); 
        #50000;

        $display("[SIM COMPLETE] Shutting down testing rig.");
        $finish;
    end
endmodule

sim/waveform.vcd
$date
	Mon Jun 22 16:52:41 2026
$end
$version
	Icarus Verilog
$end
$timescale
	1ps
$end
$scope module uart_rx_tb $end
$var wire 1 ! tb_s_tick $end
$var wire 1 " tb_rx_done $end
$var wire 8 # tb_rx_data [7:0] $end
$var wire 1 $ tb_parity_error $end
$var parameter 32 % BAUD_PERIOD $end
$var reg 1 & tb_clk $end
$var reg 1 ' tb_reset $end
$var reg 1 ( tb_rx $end
$scope module uut_baud $end
$var wire 1 & clk $end
$var wire 1 ' reset $end
$var wire 1 ! baud_tick $end
$var parameter 32 ) baud_rate $end
$var parameter 32 * clk_freq $end
$var parameter 64 + divisor $end
$var parameter 32 , oversample $end
$var reg 13 - counter [12:0] $end
$upscope $end
$scope module uut_rx $end
$var wire 1 & clk $end
$var wire 1 ' reset $end
$var wire 1 ( rx $end
$var wire 1 ! s_tick $end
$var wire 1 . calc_parity $end
$var parameter 3 / DATA $end
$var parameter 3 0 IDLE $end
$var parameter 3 1 PARITY $end
$var parameter 32 2 PARITY_TYPE $end
$var parameter 3 3 START $end
$var parameter 3 4 STOP $end
$var parameter 32 5 baud_rate $end
$var parameter 32 6 clk_freq $end
$var parameter 32 7 oversample $end
$var reg 3 8 bit_index [2:0] $end
$var reg 3 9 current_state [2:0] $end
$var reg 8 : data_buffer [7:0] $end
$var reg 3 ; next_state [2:0] $end
$var reg 1 < parity_bit $end
$var reg 1 $ parity_error $end
$var reg 8 = rx_data [7:0] $end
$var reg 1 " rx_done $end
$var reg 4 > s_count [3:0] $end
$upscope $end
$scope task send_corrupted_frame $end
$var reg 8 ? test_byte [7:0] $end
$var integer 32 @ i [31:0] $end
$upscope $end
$scope task send_uart_frame $end
$var reg 1 A calc_even_parity $end
$var reg 8 B test_byte [7:0] $end
$var integer 32 C i [31:0] $end
$upscope $end
$upscope $end
$enddefinitions $end
$comment Show the parameter values. $end
$dumpall
b10000 7
b11110100001001000000 6
b10010110000000 5
b100 4
b1 3
b0 2
b11 1
b0 0
b10 /
b10000 ,
b110 +
b11110100001001000000 *
b10010110000000 )
b11001011011100110 %
$end
#0
$dumpvars
bx C
bx B
xA
bx @
bx ?
b0 >
b0 =
0<
b0 ;
b0 :
b0 9
b0 8
0.
b0 -
1(
1'
0&
0$
b0 #
0"
0!
$end
#500000
1&
#1000000
0&
#1500000
1&
#2000000
0&
0'
#2500000
b1 -
1&
#3000000
0&
#3500000
b10 -
1&
#4000000
0&
#4500000
b11 -
1&
#5000000
0&
#5500000
b100 -
1&
#6000000
0&
#6500000
1!
b101 -
1&
#7000000
b1 ;
0&
0(
0A
b10101010 B
#7500000
0!
b0 -
b1 9
1&
#8000000
0&
#8500000
b1 -
1&
#9000000
0&
#9500000
b10 -
1&
#10000000
0&
#10500000
b11 -
1&
#11000000
0&
#11500000
b100 -
1&
#12000000
0&
#12500000
1!
b101 -
1&
#13000000
0&
#13500000
0!
b0 -
b1 >
1&
#14000000
0&
#14500000
b1 -
1&
#15000000
0&
#15500000
b10 -
1&
#16000000
0&
#16500000
b11 -
1&
#17000000
0&
#17500000
b100 -
1&
#18000000
0&
#18500000
1!
b101 -
1&
#19000000
0&
#19500000
0!
b0 -
b10 >
1&
#20000000
0&
#20500000
b1 -
1&
#21000000
0&
#21500000
b10 -
1&
#22000000
0&
#22500000
b11 -
1&
#23000000
0&
#23500000
b100 -
1&
#24000000
0&
#24500000
1!
b101 -
1&
#25000000
0&
#25500000
0!
b0 -
b11 >
1&
#26000000
0&
#26500000
b1 -
1&
#27000000
0&
#27500000
b10 -
1&
#28000000
0&
#28500000
b11 -
1&
#29000000
0&
#29500000
b100 -
1&
#30000000
0&
#30500000
1!
b101 -
1&
#31000000
0&
#31500000
0!
b0 -
b100 >
1&
#32000000
0&
#32500000
b1 -
1&
#33000000
0&
#33500000
b10 -
1&
#34000000
0&
#34500000
b11 -
1&
#35000000
0&
#35500000
b100 -
1&
#36000000
0&
#36500000
1!
b101 -
1&
#37000000
0&
#37500000
0!
b0 -
b101 >
1&
#38000000
0&
#38500000
b1 -
1&
#39000000
0&
#39500000
b10 -
1&
#40000000
0&
#40500000
b11 -
1&
#41000000
0&
#41500000
b100 -
1&
#42000000
0&
#42500000
1!
b101 -
1&
#43000000
0&
#43500000
0!
b0 -
b110 >
1&
#44000000
0&
#44500000
b1 -
1&
#45000000
0&
#45500000
b10 -
1&
#46000000
0&
#46500000
b11 -
1&
#47000000
0&
#47500000
b100 -
1&
#48000000
0&
#48500000
1!
b101 -
1&
#49000000
0&
#49500000
0!
b1 ;
b0 -
b111 >
1&
#50000000
0&
#50500000
b1 -
1&
#51000000
0&
#51500000
b10 -
1&
#52000000
0&
#52500000
b11 -
1&
#53000000
0&
#53500000
b100 -
1&
#54000000
0&
#54500000
b10 ;
1!
b101 -
1&
#55000000
0&
#55500000
0!
b0 -
b0 >
b10 9
1&
#56000000
0&
#56500000
b1 -
1&
#57000000
0&
#57500000
b10 -
1&
#58000000
0&
#58500000
b11 -
1&
#59000000
0&
#59500000
b100 -
1&
#60000000
0&
#60500000
1!
b101 -
1&
#61000000
0&
#61500000
0!
b0 -
b1 >
1&
#62000000
0&
#62500000
b1 -
1&
#63000000
0&
#63500000
b10 -
1&
#64000000
0&
#64500000
b11 -
1&
#65000000
0&
#65500000
b100 -
1&
#66000000
0&
#66500000
1!
b101 -
1&
#67000000
0&
#67500000
0!
b0 -
b10 >
1&
#68000000
0&
#68500000
b1 -
1&
#69000000
0&
#69500000
b10 -
1&
#70000000
0&
#70500000
b11 -
1&
#71000000
0&
#71500000
b100 -
1&
#72000000
0&
#72500000
1!
b101 -
1&
#73000000
0&
#73500000
0!
b0 -
b11 >
1&
#74000000
0&
#74500000
b1 -
1&
#75000000
0&
#75500000
b10 -
1&
#76000000
0&
#76500000
b11 -
1&
#77000000
0&
#77500000
b100 -
1&
#78000000
0&
#78500000
1!
b101 -
1&
#79000000
0&
#79500000
0!
b0 -
b100 >
1&
#80000000
0&
#80500000
b1 -
1&
#81000000
0&
#81500000
b10 -
1&
#82000000
0&
#82500000
b11 -
1&
#83000000
0&
#83500000
b100 -
1&
#84000000
0&
#84500000
1!
b101 -
1&
#85000000
0&
#85500000
0!
b0 -
b101 >
1&
#86000000
0&
#86500000
b1 -
1&
#87000000
0&
#87500000
b10 -
1&
#88000000
0&
#88500000
b11 -
1&
#89000000
0&
#89500000
b100 -
1&
#90000000
0&
#90500000
1!
b101 -
1&
#91000000
0&
#91500000
0!
b0 -
b110 >
1&
#92000000
0&
#92500000
b1 -
1&
#93000000
0&
#93500000
b10 -
1&
#94000000
0&
#94500000
b11 -
1&
#95000000
0&
#95500000
b100 -
1&
#96000000
0&
#96500000
1!
b101 -
1&
#97000000
0&
#97500000
0!
b0 -
b111 >
1&
#98000000
0&
#98500000
b1 -
1&
#99000000
0&
#99500000
b10 -
1&
#100000000
0&
#100500000
b11 -
1&
#101000000
0&
#101500000
b100 -
1&
#102000000
0&
#102500000
1!
b101 -
1&
#103000000
0&
#103500000
0!
b0 -
b1000 >
1&
#104000000
0&
#104500000
b1 -
1&
#105000000
0&
#105500000
b10 -
1&
#106000000
0&
#106500000
b11 -
1&
#107000000
0&
#107500000
b100 -
1&
#108000000
0&
#108500000
1!
b101 -
1&
#109000000
0&
#109500000
0!
b0 -
b1001 >
1&
#110000000
0&
#110500000
b1 -
1&
#111000000
0&
#111166000
b0 C
#111500000
b10 -
1&
#112000000
0&
#112500000
b11 -
1&
#113000000
0&
#113500000
b100 -
1&
#114000000
0&
#114500000
1!
b101 -
1&
#115000000
0&
#115500000
0!
b0 -
b1010 >
1&
#116000000
0&
#116500000
b1 -
1&
#117000000
0&
#117500000
b10 -
1&
#118000000
0&
#118500000
b11 -
1&
#119000000
0&
#119500000
b100 -
1&
#120000000
0&
#120500000
1!
b101 -
1&
#121000000
0&
#121500000
0!
b0 -
b1011 >
1&
#122000000
0&
#122500000
b1 -
1&
#123000000
0&
#123500000
b10 -
1&
#124000000
0&
#124500000
b11 -
1&
#125000000
0&
#125500000
b100 -
1&
#126000000
0&
#126500000
1!
b101 -
1&
#127000000
0&
#127500000
0!
b0 -
b1100 >
1&
#128000000
0&
#128500000
b1 -
1&
#129000000
0&
#129500000
b10 -
1&
#130000000
0&
#130500000
b11 -
1&
#131000000
0&
#131500000
b100 -
1&
#132000000
0&
#132500000
1!
b101 -
1&
#133000000
0&
#133500000
0!
b0 -
b1101 >
1&
#134000000
0&
#134500000
b1 -
1&
#135000000
0&
#135500000
b10 -
1&
#136000000
0&
#136500000
b11 -
1&
#137000000
0&
#137500000
b100 -
1&
#138000000
0&
#138500000
1!
b101 -
1&
#139000000
0&
#139500000
0!
b0 -
b1110 >
1&
#140000000
0&
#140500000
b1 -
1&
#141000000
0&
#141500000
b10 -
1&
#142000000
0&
#142500000
b11 -
1&
#143000000
0&
#143500000
b100 -
1&
#144000000
0&
#144500000
1!
b101 -
1&
#145000000
0&
#145500000
0!
b0 -
b1111 >
1&
#146000000
0&
#146500000
b1 -
1&
#147000000
0&
#147500000
b10 -
1&
#148000000
0&
#148500000
b11 -
1&
#149000000
0&
#149500000
b100 -
1&
#150000000
0&
#150500000
1!
b101 -
1&
#151000000
0&
#151500000
0!
b0 -
b1 8
b0 >
1&
#152000000
0&
#152500000
b1 -
1&
#153000000
0&
#153500000
b10 -
1&
#154000000
0&
#154500000
b11 -
1&
#155000000
0&
#155500000
b100 -
1&
#156000000
0&
#156500000
1!
b101 -
1&
#157000000
0&
#157500000
0!
b0 -
b1 >
1&
#158000000
0&
#158500000
b1 -
1&
#159000000
0&
#159500000
b10 -
1&
#160000000
0&
#160500000
b11 -
1&
#161000000
0&
#161500000
b100 -
1&
#162000000
0&
#162500000
1!
b101 -
1&
#163000000
0&
#163500000
0!
b0 -
b10 >
1&
#164000000
0&
#164500000
b1 -
1&
#165000000
0&
#165500000
b10 -
1&
#166000000
0&
#166500000
b11 -
1&
#167000000
0&
#167500000
b100 -
1&
#168000000
0&
#168500000
1!
b101 -
1&
#169000000
0&
#169500000
0!
b0 -
b11 >
1&
#170000000
0&
#170500000
b1 -
1&
#171000000
0&
#171500000
b10 -
1&
#172000000
0&
#172500000
b11 -
1&
#173000000
0&
#173500000
b100 -
1&
#174000000
0&
#174500000
1!
b101 -
1&
#175000000
0&
#175500000
0!
b0 -
b100 >
1&
#176000000
0&
#176500000
b1 -
1&
#177000000
0&
#177500000
b10 -
1&
#178000000
0&
#178500000
b11 -
1&
#179000000
0&
#179500000
b100 -
1&
#180000000
0&
#180500000
1!
b101 -
1&
#181000000
0&
#181500000
0!
b0 -
b101 >
1&
#182000000
0&
#182500000
b1 -
1&
#183000000
0&
#183500000
b10 -
1&
#184000000
0&
#184500000
b11 -
1&
#185000000
0&
#185500000
b100 -
1&
#186000000
0&
#186500000
1!
b101 -
1&
#187000000
0&
#187500000
0!
b0 -
b110 >
1&
#188000000
0&
#188500000
b1 -
1&
#189000000
0&
#189500000
b10 -
1&
#190000000
0&
#190500000
b11 -
1&
#191000000
0&
#191500000
b100 -
1&
#192000000
0&
#192500000
1!
b101 -
1&
#193000000
0&
#193500000
0!
b0 -
b111 >
1&
#194000000
0&
#194500000
b1 -
1&
#195000000
0&
#195500000
b10 -
1&
#196000000
0&
#196500000
b11 -
1&
#197000000
0&
#197500000
b100 -
1&
#198000000
0&
#198500000
1!
b101 -
1&
#199000000
0&
#199500000
0!
b0 -
b1000 >
1&
#200000000
0&
#200500000
b1 -
1&
#201000000
0&
#201500000
b10 -
1&
#202000000
0&
#202500000
b11 -
1&
#203000000
0&
#203500000
b100 -
1&
#204000000
0&
#204500000
1!
b101 -
1&
#205000000
0&
#205500000
0!
b0 -
b1001 >
1&
#206000000
0&
#206500000
b1 -
1&
#207000000
0&
#207500000
b10 -
1&
#208000000
0&
#208500000
b11 -
1&
#209000000
0&
#209500000
b100 -
1&
#210000000
0&
#210500000
1!
b101 -
1&
#211000000
0&
#211500000
0!
b0 -
b1010 >
1&
#212000000
0&
#212500000
b1 -
1&
#213000000
0&
#213500000
b10 -
1&
#214000000
0&
#214500000
b11 -
1&
#215000000
0&
#215332000
1(
b1 C
#215500000
b100 -
1&
#216000000
0&
#216500000
1!
b101 -
1&
#217000000
0&
#217500000
0!
b0 -
b1011 >
1&
#218000000
0&
#218500000
b1 -
1&
#219000000
0&
#219500000
b10 -
1&
#220000000
0&
#220500000
b11 -
1&
#221000000
0&
#221500000
b100 -
1&
#222000000
0&
#222500000
1!
b101 -
1&
#223000000
0&
#223500000
0!
b0 -
b1100 >
1&
#224000000
0&
#224500000
b1 -
1&
#225000000
0&
#225500000
b10 -
1&
#226000000
0&
#226500000
b11 -
1&
#227000000
0&
#227500000
b100 -
1&
#228000000
0&
#228500000
1!
b101 -
1&
#229000000
0&
#229500000
0!
b0 -
b1101 >
1&
#230000000
0&
#230500000
b1 -
1&
#231000000
0&
#231500000
b10 -
1&
#232000000
0&
#232500000
b11 -
1&
#233000000
0&
#233500000
b100 -
1&
#234000000
0&
#234500000
1!
b101 -
1&
#235000000
0&
#235500000
0!
b0 -
b1110 >
1&
#236000000
0&
#236500000
b1 -
1&
#237000000
0&
#237500000
b10 -
1&
#238000000
0&
#238500000
b11 -
1&
#239000000
0&
#239500000
b100 -
1&
#240000000
0&
#240500000
1!
b101 -
1&
#241000000
0&
#241500000
0!
b0 -
b1111 >
1&
#242000000
0&
#242500000
b1 -
1&
#243000000
0&
#243500000
b10 -
1&
#244000000
0&
#244500000
b11 -
1&
#245000000
0&
#245500000
b100 -
1&
#246000000
0&
#246500000
1!
b101 -
1&
#247000000
0&
#247500000
0!
b0 -
b10 8
1.
b10000000 :
b0 >
1&
#248000000
0&
#248500000
b1 -
1&
#249000000
0&
#249500000
b10 -
1&
#250000000
0&
#250500000
b11 -
1&
#251000000
0&
#251500000
b100 -
1&
#252000000
0&
#252500000
1!
b101 -
1&
#253000000
0&
#253500000
0!
b0 -
b1 >
1&
#254000000
0&
#254500000
b1 -
1&
#255000000
0&
#255500000
b10 -
1&
#256000000
0&
#256500000
b11 -
1&
#257000000
0&
#257500000
b100 -
1&
#258000000
0&
#258500000
1!
b101 -
1&
#259000000
0&
#259500000
0!
b0 -
b10 >
1&
#260000000
0&
#260500000
b1 -
1&
#261000000
0&
#261500000
b10 -
1&
#262000000
0&
#262500000
b11 -
1&
#263000000
0&
#263500000
b100 -
1&
#264000000
0&
#264500000
1!
b101 -
1&
#265000000
0&
#265500000
0!
b0 -
b11 >
1&
#266000000
0&
#266500000
b1 -
1&
#267000000
0&
#267500000
b10 -
1&
#268000000
0&
#268500000
b11 -
1&
#269000000
0&
#269500000
b100 -
1&
#270000000
0&
#270500000
1!
b101 -
1&
#271000000
0&
#271500000
0!
b0 -
b100 >
1&
#272000000
0&
#272500000
b1 -
1&
#273000000
0&
#273500000
b10 -
1&
#274000000
0&
#274500000
b11 -
1&
#275000000
0&
#275500000
b100 -
1&
#276000000
0&
#276500000
1!
b101 -
1&
#277000000
0&
#277500000
0!
b0 -
b101 >
1&
#278000000
0&
#278500000
b1 -
1&
#279000000
0&
#279500000
b10 -
1&
#280000000
0&
#280500000
b11 -
1&
#281000000
0&
#281500000
b100 -
1&
#282000000
0&
#282500000
1!
b101 -
1&
#283000000
0&
#283500000
0!
b0 -
b110 >
1&
#284000000
0&
#284500000
b1 -
1&
#285000000
0&
#285500000
b10 -
1&
#286000000
0&
#286500000
b11 -
1&
#287000000
0&
#287500000
b100 -
1&
#288000000
0&
#288500000
1!
b101 -
1&
#289000000
0&
#289500000
0!
b0 -
b111 >
1&
#290000000
0&
#290500000
b1 -
1&
#291000000
0&
#291500000
b10 -
1&
#292000000
0&
#292500000
b11 -
1&
#293000000
0&
#293500000
b100 -
1&
#294000000
0&
#294500000
1!
b101 -
1&
#295000000
0&
#295500000
0!
b0 -
b1000 >
1&
#296000000
0&
#296500000
b1 -
1&
#297000000
0&
#297500000
b10 -
1&
#298000000
0&
#298500000
b11 -
1&
#299000000
0&
#299500000
b100 -
1&
#300000000
0&
#300500000
1!
b101 -
1&
#301000000
0&
#301500000
0!
b0 -
b1001 >
1&
#302000000
0&
#302500000
b1 -
1&
#303000000
0&
#303500000
b10 -
1&
#304000000
0&
#304500000
b11 -
1&
#305000000
0&
#305500000
b100 -
1&
#306000000
0&
#306500000
1!
b101 -
1&
#307000000
0&
#307500000
0!
b0 -
b1010 >
1&
#308000000
0&
#308500000
b1 -
1&
#309000000
0&
#309500000
b10 -
1&
#310000000
0&
#310500000
b11 -
1&
#311000000
0&
#311500000
b100 -
1&
#312000000
0&
#312500000
1!
b101 -
1&
#313000000
0&
#313500000
0!
b0 -
b1011 >
1&
#314000000
0&
#314500000
b1 -
1&
#315000000
0&
#315500000
b10 -
1&
#316000000
0&
#316500000
b11 -
1&
#317000000
0&
#317500000
b100 -
1&
#318000000
0&
#318500000
1!
b101 -
1&
#319000000
0&
#319498000
0(
b10 C
#319500000
0!
b0 -
b1100 >
1&
#320000000
0&
#320500000
b1 -
1&
#321000000
0&
#321500000
b10 -
1&
#322000000
0&
#322500000
b11 -
1&
#323000000
0&
#323500000
b100 -
1&
#324000000
0&
#324500000
1!
b101 -
1&
#325000000
0&
#325500000
0!
b0 -
b1101 >
1&
#326000000
0&
#326500000
b1 -
1&
#327000000
0&
#327500000
b10 -
1&
#328000000
0&
#328500000
b11 -
1&
#329000000
0&
#329500000
b100 -
1&
#330000000
0&
#330500000
1!
b101 -
1&
#331000000
0&
#331500000
0!
b0 -
b1110 >
1&
#332000000
0&
#332500000
b1 -
1&
#333000000
0&
#333500000
b10 -
1&
#334000000
0&
#334500000
b11 -
1&
#335000000
0&
#335500000
b100 -
1&
#336000000
0&
#336500000
1!
b101 -
1&
#337000000
0&
#337500000
0!
b0 -
b1111 >
1&
#338000000
0&
#338500000
b1 -
1&
#339000000
0&
#339500000
b10 -
1&
#340000000
0&
#340500000
b11 -
1&
#341000000
0&
#341500000
b100 -
1&
#342000000
0&
#342500000
1!
b101 -
1&
#343000000
0&
#343500000
0!
b0 -
b11 8
b1000000 :
b0 >
1&
#344000000
0&
#344500000
b1 -
1&
#345000000
0&
#345500000
b10 -
1&
#346000000
0&
#346500000
b11 -
1&
#347000000
0&
#347500000
b100 -
1&
#348000000
0&
#348500000
1!
b101 -
1&
#349000000
0&
#349500000
0!
b0 -
b1 >
1&
#350000000
0&
#350500000
b1 -
1&
#351000000
0&
#351500000
b10 -
1&
#352000000
0&
#352500000
b11 -
1&
#353000000
0&
#353500000
b100 -
1&
#354000000
0&
#354500000
1!
b101 -
1&
#355000000
0&
#355500000
0!
b0 -
b10 >
1&
#356000000
0&
#356500000
b1 -
1&
#357000000
0&
#357500000
b10 -
1&
#358000000
0&
#358500000
b11 -
1&
#359000000
0&
#359500000
b100 -
1&
#360000000
0&
#360500000
1!
b101 -
1&
#361000000
0&
#361500000
0!
b0 -
b11 >
1&
#362000000
0&
#362500000
b1 -
1&
#363000000
0&
#363500000
b10 -
1&
#364000000
0&
#364500000
b11 -
1&
#365000000
0&
#365500000
b100 -
1&
#366000000
0&
#366500000
1!
b101 -
1&
#367000000
0&
#367500000
0!
b0 -
b100 >
1&
#368000000
0&
#368500000
b1 -
1&
#369000000
0&
#369500000
b10 -
1&
#370000000
0&
#370500000
b11 -
1&
#371000000
0&
#371500000
b100 -
1&
#372000000
0&
#372500000
1!
b101 -
1&
#373000000
0&
#373500000
0!
b0 -
b101 >
1&
#374000000
0&
#374500000
b1 -
1&
#375000000
0&
#375500000
b10 -
1&
#376000000
0&
#376500000
b11 -
1&
#377000000
0&
#377500000
b100 -
1&
#378000000
0&
#378500000
1!
b101 -
1&
#379000000
0&
#379500000
0!
b0 -
b110 >
1&
#380000000
0&
#380500000
b1 -
1&
#381000000
0&
#381500000
b10 -
1&
#382000000
0&
#382500000
b11 -
1&
#383000000
0&
#383500000
b100 -
1&
#384000000
0&
#384500000
1!
b101 -
1&
#385000000
0&
#385500000
0!
b0 -
b111 >
1&
#386000000
0&
#386500000
b1 -
1&
#387000000
0&
#387500000
b10 -
1&
#388000000
0&
#388500000
b11 -
1&
#389000000
0&
#389500000
b100 -
1&
#390000000
0&
#390500000
1!
b101 -
1&
#391000000
0&
#391500000
0!
b0 -
b1000 >
1&
#392000000
0&
#392500000
b1 -
1&
#393000000
0&
#393500000
b10 -
1&
#394000000
0&
#394500000
b11 -
1&
#395000000
0&
#395500000
b100 -
1&
#396000000
0&
#396500000
1!
b101 -
1&
#397000000
0&
#397500000
0!
b0 -
b1001 >
1&
#398000000
0&
#398500000
b1 -
1&
#399000000
0&
#399500000
b10 -
1&
#400000000
0&
#400500000
b11 -
1&
#401000000
0&
#401500000
b100 -
1&
#402000000
0&
#402500000
1!
b101 -
1&
#403000000
0&
#403500000
0!
b0 -
b1010 >
1&
#404000000
0&
#404500000
b1 -
1&
#405000000
0&
#405500000
b10 -
1&
#406000000
0&
#406500000
b11 -
1&
#407000000
0&
#407500000
b100 -
1&
#408000000
0&
#408500000
1!
b101 -
1&
#409000000
0&
#409500000
0!
b0 -
b1011 >
1&
#410000000
0&
#410500000
b1 -
1&
#411000000
0&
#411500000
b10 -
1&
#412000000
0&
#412500000
b11 -
1&
#413000000
0&
#413500000
b100 -
1&
#414000000
0&
#414500000
1!
b101 -
1&
#415000000
0&
#415500000
0!
b0 -
b1100 >
1&
#416000000
0&
#416500000
b1 -
1&
#417000000
0&
#417500000
b10 -
1&
#418000000
0&
